{"id":"f3f6a18d-6918-4637-be59-70075e92140e","timestamp":1741726661615,"matcher":{"static":{"/api/content/pages/database.sql":{"prerender":true},"/api/content/blog/database.sql":{"prerender":true},"/api/content/directory/database.sql":{"prerender":true}},"wildcard":{},"dynamic":{}},"prerendered":["/","/express-home-loans","/got-keyd-realty","/sneaker-legends","/rapidhomeloans","/tags/websites","/tags/consulting","/tags/mortgage","/tags/clothing","/tags/shoes","/tech-by-tiba","/privacy-policy","/terms-of-service","/tags/realestate","/blog","/advertise","/tags/IT","/tags/real estate","/submit","/blog/blog-post-1"]}